odoo/addons/base_location/README.rst
odoo/addons/base_location/__init__.py
odoo/addons/base_location/__manifest__.py
odoo/addons/base_location/demo/res_city_zip.xml
odoo/addons/base_location/i18n/am.po
odoo/addons/base_location/i18n/ar.po
odoo/addons/base_location/i18n/base_location.pot
odoo/addons/base_location/i18n/bg.po
odoo/addons/base_location/i18n/bs.po
odoo/addons/base_location/i18n/ca.po
odoo/addons/base_location/i18n/cs.po
odoo/addons/base_location/i18n/da.po
odoo/addons/base_location/i18n/de.po
odoo/addons/base_location/i18n/el_GR.po
odoo/addons/base_location/i18n/en_GB.po
odoo/addons/base_location/i18n/es.po
odoo/addons/base_location/i18n/es_AR.po
odoo/addons/base_location/i18n/es_CL.po
odoo/addons/base_location/i18n/es_CO.po
odoo/addons/base_location/i18n/es_CR.po
odoo/addons/base_location/i18n/es_DO.po
odoo/addons/base_location/i18n/es_EC.po
odoo/addons/base_location/i18n/es_MX.po
odoo/addons/base_location/i18n/es_PE.po
odoo/addons/base_location/i18n/es_PY.po
odoo/addons/base_location/i18n/es_VE.po
odoo/addons/base_location/i18n/et.po
odoo/addons/base_location/i18n/eu.po
odoo/addons/base_location/i18n/fa.po
odoo/addons/base_location/i18n/fi.po
odoo/addons/base_location/i18n/fr.po
odoo/addons/base_location/i18n/fr_CA.po
odoo/addons/base_location/i18n/fr_CH.po
odoo/addons/base_location/i18n/gl.po
odoo/addons/base_location/i18n/gl_ES.po
odoo/addons/base_location/i18n/he.po
odoo/addons/base_location/i18n/hr.po
odoo/addons/base_location/i18n/hr_HR.po
odoo/addons/base_location/i18n/hu.po
odoo/addons/base_location/i18n/id.po
odoo/addons/base_location/i18n/it.po
odoo/addons/base_location/i18n/ja.po
odoo/addons/base_location/i18n/ko.po
odoo/addons/base_location/i18n/lt.po
odoo/addons/base_location/i18n/lt_LT.po
odoo/addons/base_location/i18n/lv.po
odoo/addons/base_location/i18n/mk.po
odoo/addons/base_location/i18n/mn.po
odoo/addons/base_location/i18n/nb.po
odoo/addons/base_location/i18n/nb_NO.po
odoo/addons/base_location/i18n/nl.po
odoo14_addon_base_location-14.0.1.2.5.dist-info/METADATA
odoo14_addon_base_location-14.0.1.2.5.dist-info/WHEEL
odoo14_addon_base_location-14.0.1.2.5.dist-info/top_level.txt
odoo14_addon_base_location-14.0.1.2.5.dist-info/RECORD
